vizitig/__init__.py
vizitig/__main__.py
vizitig/cli.py
vizitig/env_var.py
vizitig/errors.py
vizitig/generate_graph.py
vizitig/info.py
vizitig/metadata.py
vizitig/parsing.py
vizitig/paths.py
vizitig/queries.md
vizitig/run.py
vizitig/utils.py
vizitig/annotate/__init__.py
vizitig/api/__init__.py
vizitig/api/async_utils.py
vizitig/api/errors.py
vizitig/api/main.py
vizitig/api/path.py
vizitig/api/types.py
vizitig/color/__init__.py
vizitig/color/bulk_update.py
vizitig/export/__init__.py
vizitig/genes/__init__.py
vizitig/index/__init__.py
vizitig/index/classes.py
vizitig/index/rust_index.py
vizitig/index/sqlite_index.py
vizitig/query/__init__.py
vizitig/query/query.py
vizitig/search/__init__.py
vizitig/tests/__init__.py
vizitig/tests/conftest.py
vizitig/tests/test_export.py
vizitig/tests/test_fixture.py
vizitig/tests/test_index.py
vizitig/tests/test_query.py
vizitig/tests/test_typing.py
vizitig/tests/test_vizibridge.py
vizitig/types/__init__.py
vizitig/data/site/graph.html
vizitig/data/site/index.html
vizitig/data/site/logo.png
vizitig/data/site/selfloop.svg
vizitig/data/site/test.html
vizitig/data/site/css/style.css
vizitig/data/site/js/aligner.js
vizitig/data/site/js/api.js
vizitig/data/site/js/application.js
vizitig/data/site/js/config.js
vizitig/data/site/js/d3_default.js
vizitig/data/site/js/d3_viz.js
vizitig/data/site/js/dna_utils.js
vizitig/data/site/js/eval_dsl.js
vizitig/data/site/js/filters.js
vizitig/data/site/js/geo.js
vizitig/data/site/js/graphviz_worker.js
vizitig/data/site/js/ico.js
vizitig/data/site/js/layouts.js
vizitig/data/site/js/logger.js
vizitig/data/site/js/main.js
vizitig/data/site/js/metadata.js
vizitig/data/site/js/ui.js
vizitig/data/site/js/utils.js
vizitig/data/site/js/visualisation.js
vizitig/data/site/js/welcome.js
vizitig/data/site/js/viz/bands_graph.js
vizitig/data/site/js/viz/simple_graph.js
vizitig/data/site/js/viz/table.js
vizitig/data/site/js/viz_actions/d3_actions.js
vizitig/data/site/js/viz_actions/default_actions.js
vizitig-1.0.5.dist-info/METADATA
vizitig-1.0.5.dist-info/WHEEL
vizitig-1.0.5.dist-info/entry_points.txt
vizitig-1.0.5.dist-info/licenses/LICENSE.txt
vizitig-1.0.5.dist-info/RECORD
