Metadata-Version: 2.4
Name: vizitig
Version: 1.0.5
Summary: A python manipulation and visualization of genomic graph data
Project-URL: Repository, https://gitlab.inria.fr/vizisoft/vizitig
Author-email: Charles Paperman <charles.paperman@univ-lille.fr>, Camille Marchet <camille.marchet@univ-lille.fr>
License-Expression: BSD-3-Clause
License-File: LICENSE.txt
Keywords: BCALM,DNA,De Brujn Graph,RNA,graph,kmer,visualization
Classifier: Development Status :: 4 - Beta
Classifier: License :: OSI Approved :: BSD License
Classifier: Topic :: Scientific/Engineering :: Bio-Informatics
Requires-Python: >=3.9
Requires-Dist: fastapi
Requires-Dist: lark
Requires-Dist: networkdisk
Requires-Dist: psutil
Requires-Dist: pydantic-extra-types
Requires-Dist: python-multipart
Requires-Dist: requests
Requires-Dist: tabulate
Requires-Dist: types-requests
Requires-Dist: typing-extensions
Requires-Dist: uvicorn
Requires-Dist: vizibridge>=0.5.0; platform_system == 'Linux' and platform_machine == 'x86_64'
Requires-Dist: vizibridge>=0.5.0; platform_system == 'darwin' and platform_machine == 'aarch64'
Provides-Extra: all
Requires-Dist: mypy; extra == 'all'
Requires-Dist: pytest; extra == 'all'
Requires-Dist: pytest-cov; extra == 'all'
Requires-Dist: pytest-env; extra == 'all'
Requires-Dist: ruff; extra == 'all'
Requires-Dist: types-networkx; extra == 'all'
Requires-Dist: types-psutil; extra == 'all'
Requires-Dist: types-tabulate; extra == 'all'
Requires-Dist: types-tqdm; extra == 'all'
Provides-Extra: dev
Requires-Dist: mypy; extra == 'dev'
Requires-Dist: pytest; extra == 'dev'
Requires-Dist: pytest-cov; extra == 'dev'
Requires-Dist: pytest-env; extra == 'dev'
Requires-Dist: ruff; extra == 'dev'
Requires-Dist: types-networkx; extra == 'dev'
Requires-Dist: types-psutil; extra == 'dev'
Requires-Dist: types-tabulate; extra == 'dev'
Requires-Dist: types-tqdm; extra == 'dev'
